Metadata-Version: 2.1
Name: kekwutils
Version: 0.2.1
Summary: Number Utilities package
Home-page: https://github.com/kekw/utils
Author: Dmitry Polchinsky
Author-email: 284549@niuitmo.ru
License: UNKNOWN
Platform: UNKNOWN
